say_hi_mcp/__init__.py
say_hi_mcp/py.typed
say_hi_mcp/server.py
say_hi_mcp-0.1.23.dist-info/licenses/LICENSE
say_hi_mcp-0.1.23.dist-info/METADATA
say_hi_mcp-0.1.23.dist-info/WHEEL
say_hi_mcp-0.1.23.dist-info/entry_points.txt
say_hi_mcp-0.1.23.dist-info/top_level.txt
say_hi_mcp-0.1.23.dist-info/RECORD
