Metadata-Version: 2.4
Name: say-hi-mcp
Version: 0.1.23
Summary: 一个简单的MCP Server示例，提供向不同人打招呼的工具
Author-email: Your Name <your.email@example.com>
Maintainer-email: Your Name <your.email@example.com>
License-Expression: MIT
Project-URL: Homepage, https://github.com/yourusername/say-hi-mcp
Project-URL: Repository, https://github.com/yourusername/say-hi-mcp.git
Project-URL: Issues, https://github.com/yourusername/say-hi-mcp/issues
Project-URL: Changelog, https://github.com/yourusername/say-hi-mcp/blob/main/CHANGELOG.md
Keywords: mcp,server,chat,ai,anthropic
Classifier: Development Status :: 3 - Alpha
Classifier: Intended Audience :: Developers
Classifier: Operating System :: OS Independent
Classifier: Programming Language :: Python :: 3
Classifier: Programming Language :: Python :: 3.10
Classifier: Programming Language :: Python :: 3.11
Classifier: Programming Language :: Python :: 3.12
Classifier: Programming Language :: Python :: 3.13
Classifier: Topic :: Software Development :: Libraries :: Python Modules
Classifier: Topic :: Communications :: Chat
Requires-Python: >=3.10
License-File: LICENSE
Requires-Dist: black>=25.1.0
Requires-Dist: isort>=6.0.1
Requires-Dist: mcp[cli]>=1.2.0
Requires-Dist: pydantic>=2.0.0
Requires-Dist: pytest>=8.3.5
Provides-Extra: dev
Requires-Dist: pytest>=7.0; extra == "dev"
Requires-Dist: pytest-asyncio>=0.21.0; extra == "dev"
Requires-Dist: black>=23.0; extra == "dev"
Requires-Dist: isort>=5.12; extra == "dev"
Requires-Dist: mypy>=1.0; extra == "dev"
Requires-Dist: flake8>=6.0; extra == "dev"
Dynamic: license-file
